waterEntropy/__init__.py
waterEntropy/analysis/HB.py
waterEntropy/analysis/HB_labels.py
waterEntropy/analysis/RAD.py
waterEntropy/analysis/__init__.py
waterEntropy/analysis/shell_labels.py
waterEntropy/analysis/shells.py
waterEntropy/cli/runWaterEntropy.py
waterEntropy/cli/run_find_Nc.py
waterEntropy/entropy/__init__.py
waterEntropy/entropy/convariances.py
waterEntropy/entropy/orientations.py
waterEntropy/entropy/vibrations.py
waterEntropy/maths/__init__.py
waterEntropy/maths/transformations.py
waterEntropy/maths/trig.py
waterEntropy/recipes/__init__.py
waterEntropy/recipes/bulk_water.py
waterEntropy/recipes/forces_torques.py
waterEntropy/recipes/interfacial_solvent.py
waterEntropy/utils/__init__.py
waterEntropy/utils/dask_clusters.py
waterEntropy/utils/helpers.py
waterEntropy/utils/selections.py
waterentropy-2.0.0.dist-info/entry_points.txt
waterentropy-2.0.0.dist-info/licenses/LICENSE
waterentropy-2.0.0.dist-info/WHEEL
waterentropy-2.0.0.dist-info/METADATA
waterentropy-2.0.0.dist-info/RECORD
